ipor_fusion/AccessManager.py
ipor_fusion/AnvilTestContainerStarter.py
ipor_fusion/CheatingPlasmaVaultSystemFactory.py
ipor_fusion/CheatingTransactionExecutor.py
ipor_fusion/ERC20.py
ipor_fusion/FuseMapper.py
ipor_fusion/IporFusionMarkets.py
ipor_fusion/MarketId.py
ipor_fusion/PlasmaSystem.py
ipor_fusion/PlasmaVault.py
ipor_fusion/PlasmaVaultSystemFactory.py
ipor_fusion/PlasmaVaultSystemFactoryBase.py
ipor_fusion/PriceOracleMiddleware.py
ipor_fusion/RewardsClaimManager.py
ipor_fusion/Roles.py
ipor_fusion/TransactionExecutor.py
ipor_fusion/WithdrawManager.py
ipor_fusion/__init__.py
ipor_fusion/error/FuseMappingError.py
ipor_fusion/error/UnsupportedAsset.py
ipor_fusion/error/UnsupportedChainId.py
ipor_fusion/error/UnsupportedFuseError.py
ipor_fusion/error/UnsupportedMarketError.py
ipor_fusion/error/__init__.py
ipor_fusion/fuse/AaveV3BorrowFuse.py
ipor_fusion/fuse/AaveV3SupplyFuse.py
ipor_fusion/fuse/CompoundV3SupplyFuse.py
ipor_fusion/fuse/Erc4626SupplyFuse.py
ipor_fusion/fuse/FluidInstadappSupplyFuse.py
ipor_fusion/fuse/FuseAction.py
ipor_fusion/fuse/GearboxStakeFuse.py
ipor_fusion/fuse/GearboxSupplyFuse.py
ipor_fusion/fuse/GearboxSupplyOnlyFuse.py
ipor_fusion/fuse/MorphoBlueClaimFuse.py
ipor_fusion/fuse/MorphoBlueSupplyFuse.py
ipor_fusion/fuse/MorphoFlashLoanFuse.py
ipor_fusion/fuse/RamsesClaimFuse.py
ipor_fusion/fuse/RamsesV2CollectFuse.py
ipor_fusion/fuse/RamsesV2ModifyPositionFuse.py
ipor_fusion/fuse/RamsesV2NewPositionFuse.py
ipor_fusion/fuse/UniswapV3CollectFuse.py
ipor_fusion/fuse/UniswapV3ModifyPositionFuse.py
ipor_fusion/fuse/UniswapV3NewPositionFuse.py
ipor_fusion/fuse/UniswapV3SwapFuse.py
ipor_fusion/fuse/UniversalTokenSwapperFuse.py
ipor_fusion/fuse/__init__.py
ipor_fusion/helpers/Addresses.py
ipor_fusion/helpers/AerodromeSwapHelper.py
ipor_fusion/helpers/BalanceLogger.py
ipor_fusion/markets/AaveV3Market.py
ipor_fusion/markets/CompoundV3Market.py
ipor_fusion/markets/ERC4626Market.py
ipor_fusion/markets/FluidInstadappMarket.py
ipor_fusion-0.23.0.dist-info/LICENSE
ipor_fusion-0.23.0.dist-info/METADATA
ipor_fusion-0.23.0.dist-info/WHEEL
ipor_fusion-0.23.0.dist-info/RECORD
