Metadata-Version: 2.3
Name: ipor_fusion
Version: 0.23.0
Summary: The IPOR Fusion SDK for Python
License: BSD-3
Keywords: ethereum,solidity,testing,development,framework
Author: Adam Mydlarz
Author-email: amydlarz@gmail.com
Requires-Python: >=3.10,<4.0
Classifier: Development Status :: 5 - Production/Stable
Classifier: Environment :: Console
Classifier: Intended Audience :: Developers
Classifier: Intended Audience :: Financial and Insurance Industry
Classifier: License :: OSI Approved :: BSD License
Classifier: License :: Other/Proprietary License
Classifier: Natural Language :: English
Classifier: Operating System :: OS Independent
Classifier: Programming Language :: Cython
Classifier: Programming Language :: Python
Classifier: Programming Language :: Python :: 3
Classifier: Programming Language :: Python :: 3.10
Classifier: Programming Language :: Python :: 3.11
Classifier: Programming Language :: Python :: 3.12
Classifier: Programming Language :: Python :: 3.13
Classifier: Programming Language :: Python :: 3 :: Only
Classifier: Topic :: Office/Business
Classifier: Topic :: Office/Business :: Financial
Classifier: Topic :: Office/Business :: Financial :: Accounting
Classifier: Topic :: Office/Business :: Financial :: Investment
Classifier: Topic :: Software Development :: Libraries :: Python Modules
Classifier: Topic :: Utilities
Requires-Dist: eth-abi (>=5.1.0,<6.0.0)
Requires-Dist: eth-typing (>=5.0.0,<6.0.0)
Requires-Dist: python-dotenv (>=1.0.1,<2.0.0)
Requires-Dist: web3 (>=7.7.0,<8.0.0)
Project-URL: Documentation, https://docs.ipor.io/ipor-fusion/fusion-introduction
Project-URL: Homepage, https://ipor.io
Project-URL: Repository, https://github.com/IPOR-Labs/ipor-fusion.py
